MANIFEST.in
setup.py
netos_reporting/__init__.py
netos_reporting/filtersets.py
netos_reporting/forms.py
netos_reporting/models.py
netos_reporting/navigation.py
netos_reporting/tables.py
netos_reporting/urls.py
netos_reporting/views.py
netos_reporting.egg-info/PKG-INFO
netos_reporting.egg-info/SOURCES.txt
netos_reporting.egg-info/dependency_links.txt
netos_reporting.egg-info/not-zip-safe
netos_reporting.egg-info/top_level.txt
netos_reporting/api/__init__.py
netos_reporting/api/serializers.py
netos_reporting/api/urls.py
netos_reporting/api/views.py
netos_reporting/migrations/0001_initial.py
netos_reporting/migrations/__init__.py
netos_reporting/static/netos_reporting/js/hardware_report.js
netos_reporting/static/netos_reporting/js/software_report.js
netos_reporting/templates/netos_reporting/base_detail.html
netos_reporting/templates/netos_reporting/base_report.html
netos_reporting/templates/netos_reporting/eol_threshold.html
netos_reporting/templates/netos_reporting/netoseolreportdevice.html
netos_reporting/templates/netos_reporting/netoseolreportinventory.html
netos_reporting/templates/netos_reporting/netoseolreportmodule.html
netos_reporting/templates/netos_reporting/netoshardware.html
netos_reporting/templates/netos_reporting/netoshardware_report.html
netos_reporting/templates/netos_reporting/netoshardwarereport_list.html
netos_reporting/templates/netos_reporting/netossoftwarereport.html
netos_reporting/templates/netos_reporting/netossoftwarereport_list.html
netos_reporting/templatetags/__init__.py
netos_reporting/templatetags/eol_helpers.py