Metadata-Version: 2.1
Name: netos-reporting
Version: 0.3.0
Summary: A plugin with chart based reports
